dagos/__init__.py
dagos/__main__.py
dagos/commands/__init__.py
dagos/commands/manage/__init__.py
dagos/commands/manage/components/__init__.py
dagos/commands/manage/components/git/__init__.py
dagos/commands/manage/components/git/cli.py
dagos/commands/manage/group.py
dagos/commands/wsl/__init__.py
dagos/commands/wsl/group.py
dagos/commands/wsl/import_wsl_distro.py
dagos/commands/wsl/prepare_wsl_distro.py
dagos/console.py
dagos/main.py
dagos/utils/__init__.py
dagos/utils/wsl_utils.py
dagos-0.1.2.dist-info/LICENSE
dagos-0.1.2.dist-info/WHEEL
dagos-0.1.2.dist-info/METADATA
dagos-0.1.2.dist-info/RECORD
